atomic/__init__.py
atomic/activations/__init__.py
atomic/activations/activation.py
atomic/activations/elu.py
atomic/activations/leaky_relu.py
atomic/activations/relu.py
atomic/activations/sigmoid.py
atomic/activations/softmax.py
atomic/activations/tanh.py
atomic/core/__init__.py
atomic/core/autograd/__init__.py
atomic/core/autograd/tensor.py
atomic/core/basestructure/__init__.py
atomic/core/basestructure/base.py
atomic/layers/__init__.py
atomic/layers/conv.py
atomic/layers/dense.py
atomic/losses/__init__.py
atomic/losses/bce_loss.py
atomic/losses/cross_entropy.py
atomic/losses/loss.py
atomic/losses/mse_loss.py
atomic/losses/softmax_cross_entropy_loss.py
atomic/metrics/__init__.py
atomic/metrics/accuracy.py
atomic/models/__init__.py
atomic/models/custom.py
atomic/models/sequential.py
atomic/nlp/__init__.py
atomic/nlp/transformer.py
atomic/optimizers/__init__.py
atomic/optimizers/adam.py
atomic/optimizers/optimizer.py
atomic/optimizers/sgd.py
atomic/util/__init__.py
atomic/util/manage.py
atomic_autograd-0.1.1.dist-info/licenses/LICENSE
atomic_autograd-0.1.1.dist-info/METADATA
atomic_autograd-0.1.1.dist-info/WHEEL
atomic_autograd-0.1.1.dist-info/top_level.txt
atomic_autograd-0.1.1.dist-info/RECORD
