Metadata-Version: 2.4
Name: atomic-autograd
Version: 0.1.1
Summary: A lightweight, flexible autograd engine for deep learning
Author-email: Amir Rabah Ashour founder of atomic ai <amiralasady107@gmail.com>
License: MIT License
Project-URL: Homepage, https://github.com/AmirAlasady/atomic-autograd.git
Project-URL: Repository, https://github.com/AmirAlasady/atomic-autograd.git
Keywords: deep learning,autograd,neural network,numpy,cupy
Classifier: Development Status :: 3 - Alpha
Classifier: Intended Audience :: Developers
Classifier: Intended Audience :: Science/Research
Classifier: License :: OSI Approved :: MIT License
Classifier: Programming Language :: Python :: 3
Classifier: Programming Language :: Python :: 3.8
Classifier: Programming Language :: Python :: 3.9
Classifier: Programming Language :: Python :: 3.10
Classifier: Programming Language :: Python :: 3.11
Classifier: Topic :: Scientific/Engineering :: Artificial Intelligence
Requires-Python: >=3.8
License-File: LICENSE
Requires-Dist: numpy>=1.20.0
Requires-Dist: requests
Provides-Extra: gpu
Requires-Dist: cupy>=10.0.0; extra == "gpu"
Provides-Extra: test
Requires-Dist: pytest; extra == "test"
Dynamic: license-file
